bendy/VERSION
bendy/__init__.py
bendy/composite_cubic_bezier.py
bendy/cubic_bezier.py
bendy/logging.py
bendy/math.py
bendy/point.py
bendy/py.typed
bendy/version_func.py
bendy-1.0.0a10.dist-info/LICENSE
bendy-1.0.0a10.dist-info/METADATA
bendy-1.0.0a10.dist-info/WHEEL
bendy-1.0.0a10.dist-info/top_level.txt
bendy-1.0.0a10.dist-info/RECORD
