Metadata-Version: 2.1
Name: bendy
Version: 1.0.0a10
Summary: Bezier curve calculator
Home-page: https://github.com/cariad/bendy
Author: Cariad Eccleston
Author-email: cariad@cariad.earth
License: MIT
Classifier: Development Status :: 3 - Alpha
Classifier: License :: OSI Approved :: MIT License
Classifier: Natural Language :: English
Classifier: Operating System :: OS Independent
Classifier: Programming Language :: Python :: 3 :: Only
Classifier: Programming Language :: Python :: 3.11
Classifier: Typing :: Typed
Requires-Python: >=3.11
License-File: LICENSE
Requires-Dist: vecked ~=1.7
Provides-Extra: draw
Requires-Dist: pillow ~=10.0 ; extra == 'draw'
